pytermstyle/__init__.py
pytermstyle/custom_types.py
pytermstyle/definitions.py
pytermstyle/logger.py
pytermstyle/py.typed
pytermstyle/pytermstyle.py
pytermstyle/settings.py
pytermstyle/utils.py
pytermstyle-1.0.0.dist-info/METADATA
pytermstyle-1.0.0.dist-info/WHEEL
pytermstyle-1.0.0.dist-info/licenses/LICENSE
pytermstyle-1.0.0.dist-info/RECORD
