Metadata-Version: 2.4
Name: pytermstyle
Version: 1.0.0
Summary: ANSI color formatting for output in terminal
Project-URL: Homepage, https://github.com/SpotRusherZ/pytermstyle
Project-URL: Issues, https://github.com/SpotRusherZ/pytermstyle/issues
Author-email: Luka <spotrz.official@gmail.com>
Maintainer-email: Luka <spotrz.official@gmail.com>
License: MIT License
License-File: LICENSE
Keywords: ANSI,color,colored,colour,console,logging,terminal
Classifier: Environment :: Console
Classifier: Intended Audience :: Developers
Classifier: License :: OSI Approved :: MIT License
Classifier: Operating System :: OS Independent
Classifier: Programming Language :: Python :: 3
Classifier: Programming Language :: Python :: 3.8
Classifier: Programming Language :: Python :: 3.9
Classifier: Programming Language :: Python :: 3.10
Classifier: Programming Language :: Python :: 3.11
Classifier: Programming Language :: Python :: 3.12
Classifier: Programming Language :: Python :: 3.13
Requires-Python: >=3.8
